[{"_time":1661886167,"cribl_breaker":"Break on newlines","_raw":"08/30/2022 12:02:47 PM\r\nLogName=Security\r\nSourceName=AD FS Auditing\r\nEventCode=404\r\nEventType=0\r\nType=Information\r\nComputerName=myhost.acme.com\r\nUser=NOT_TRANSLATED\r\nSid=S-1-5-21-359538278-52765162-2211038576-184163\r\nSidType=0\r\nTaskCategory=Printers\r\nOpCode=Info\r\nRecordNumber=68106984\r\nKeywords=Audit Success, Classic\r\nMessage=An HTTP response was dispatched. See audit 510 with the same Instance ID for headers. \r\r\n\r\r\nInstance ID: 5bffc88b-3f2d-4119-b0d6-ee3d59a8934f \r\r\n\r\r\nActivity ID: fd39ceeb-54e5-440f-0e15-0080011400d2 \r\r\n\r\r\nResponse Details: \r\r\n    Date And Time: 2022-08-30 19:02:47 \r\r\n    Status Code: 200 \r\r\n    Status Description: OK","source":"WinEventLog:Security","host":"myhost.acme.com","sourcetype":"WinEventLog:Security","index":"wineventlog"}]